pytorch_wrapper/__init__.py
pytorch_wrapper/evaluators.py
pytorch_wrapper/functional.py
pytorch_wrapper/loss_wrappers.py
pytorch_wrapper/samplers.py
pytorch_wrapper/system.py
pytorch_wrapper/training_callbacks.py
pytorch_wrapper/tuner.py
pytorch_wrapper/modules/__init__.py
pytorch_wrapper/modules/dynamic_self_attention_encoder.py
pytorch_wrapper/modules/embedding_layer.py
pytorch_wrapper/modules/layer_norm.py
pytorch_wrapper/modules/mlp.py
pytorch_wrapper/modules/multi_head_attention.py
pytorch_wrapper/modules/residual.py
pytorch_wrapper/modules/sequence_basic_cnn_block.py
pytorch_wrapper/modules/sequence_basic_cnn_encoder.py
pytorch_wrapper/modules/sequence_dense_cnn.py
pytorch_wrapper/modules/sinusoidal_positional_embedding_layer.py
pytorch_wrapper/modules/softmax_attention_encoder.py
pytorch_wrapper/modules/softmax_self_attention_encoder.py
pytorch_wrapper/modules/transformer_encoder.py
pytorch_wrapper/modules/transformer_encoder_block.py
tests/modules/__init__.py
tests/modules/dynamic_self_attention_encoder_tests.py
tests/modules/embedding_layer_tests.py
tests/modules/layer_norm_tests.py
tests/modules/mlp_tests.py
tests/modules/multi_head_attention_tests.py
tests/modules/residual_tests.py
tests/modules/sequence_basic_cnn_block_tests.py
tests/modules/sequence_basic_cnn_encoder_tests.py
tests/modules/sequence_dense_cnn_tests.py
tests/modules/sinusoidal_positional_embedding_layer_tests.py
tests/modules/softmax_attention_encoder_tests.py
tests/modules/softmax_self_attention_encoder_tests.py
tests/modules/transformer_encoder_block_tests.py
tests/modules/transformer_encoder_tests.py
pytorch_wrapper-1.0.4.dist-info/LICENSE
pytorch_wrapper-1.0.4.dist-info/METADATA
pytorch_wrapper-1.0.4.dist-info/WHEEL
pytorch_wrapper-1.0.4.dist-info/top_level.txt
pytorch_wrapper-1.0.4.dist-info/RECORD
