Metadata-Version: 2.1
Name: pytorch-wrapper
Version: 1.0.4
Summary: PyTorchWrapper is a library that provides a systematic and extensible way to build, train, evaluate, and tune deep learning models using PyTorch. It also provides several ready to use modules and functions for fast model development.
Home-page: https://github.com/jkoutsikakis/pytorch-wrapper
Author: John Koutsikakis
Author-email: jkoutsikakis@gmail.com
License: UNKNOWN
Platform: UNKNOWN
Classifier: License :: OSI Approved :: MIT License
Classifier: Programming Language :: Python :: 3
Classifier: Programming Language :: Python :: 3.6
Requires-Dist: numpy (<2,>=1.14)
Requires-Dist: scikit-learn (<1,>=0.19)
Requires-Dist: six (<2,>=1.11)
Requires-Dist: torch (<2,>=1)
Requires-Dist: tqdm (<5,>=4.36.1)
Requires-Dist: hyperopt (<0.2,>=0.1)
